W_Gym/W_Gym.py
W_Gym/W_Gym_Grid2D.py
W_Gym/W_Gym_simulator.py
W_Gym/__init__.py
W_Gym-0.0.0.dist-info/METADATA
W_Gym-0.0.0.dist-info/WHEEL
W_Gym-0.0.0.dist-info/top_level.txt
W_Gym-0.0.0.dist-info/RECORD
